pyops/__init__.py
pyops/api_tools.py
pyops/cli.py
pyops/git_tools.py
pyops/linux_tools.py
pyops/logger.py
pyops/system_monitor.py
tests/__init__.py
tests/test_api_tools.py
tests/test_git_tools.py
tests/test_system_monitor.py
pyops_cli-1.0.0.dist-info/METADATA
pyops_cli-1.0.0.dist-info/WHEEL
pyops_cli-1.0.0.dist-info/entry_points.txt
pyops_cli-1.0.0.dist-info/top_level.txt
pyops_cli-1.0.0.dist-info/RECORD
