Metadata-Version: 2.4
Name: pyops-cli
Version: 1.0.0
Summary: PyOps CLI Toolkit: System Monitoring, Git Automation, Linux Commands, API Tools
Home-page: https://github.com/yourusername/pyops-cli
Author: Rohan Jadhav
Author-email: youremail@example.com
Classifier: Programming Language :: Python :: 3
Classifier: License :: OSI Approved :: MIT License
Classifier: Operating System :: OS Independent
Requires-Python: >=3.6
Requires-Dist: psutil
Requires-Dist: gitpython
Requires-Dist: requests
Requires-Dist: click
Dynamic: author
Dynamic: author-email
Dynamic: classifier
Dynamic: description
Dynamic: description-content-type
Dynamic: home-page
Dynamic: requires-dist
Dynamic: requires-python
Dynamic: summary
